{
  "build": {
    "arduino": {
      "ldscript": "esp32s2_out.ld"
    },
    "core": "esp32",
    "extra_flags": [
      "-DARDUINO_LOLIN_S2_MINI",
      "-DBOARD_HAS_PSRAM",
      "-DARDUINO_USB_CDC_ON_BOOT=1",
      "-DARDUINO_USB_MODE=0"
    ],
    "f_cpu": "240000000L",
    "f_flash": "80000000L",
    "flash_mode": "dio",
    "hwids": [
      [
        "0x256f",
        "0xc631 "
      ]
    ],
    "mcu": "esp32s2",
    "variant": "lolin_s2_mini",
    "usb_vid": "0x256f",
    "usb_pid": "0xc631",
    "usb_manufacturer": "3DCONNEXION",
    "usb_product": "SpaceMouse Pro Wireless"       
  },
  "connectivity": [
    "wifi"
  ],
  "debug": {
    "openocd_target": "esp32s2.cfg"
  },
  "frameworks": [
    "arduino",
    "espidf"
  ],
  "name": "nebujoy-s2-mini",
  "upload": {
    "flash_size": "4MB",
    "maximum_ram_size": 327680,
    "maximum_size": 4194304,
    "use_1200bps_touch": true,
    "wait_for_upload_port": true,
    "require_upload_port": true,
    "speed": 921600
  },
  "url": "https://www.wemos.cc/en/latest/s2/s2_mini.html",
  "vendor": "WEMOS"
}
